Metadata-Version: 2.1
Name: csgotm-py
Version: 0.2.0
Summary: Python module for working with Market CS:GO API
Home-page: https://github.com/wendland0d/csgotm-py
Author: wendland0d
Author-email: wendland0d@gmail.com
License: Apache License, Version 2.0, see LICENSE file
Classifier: License :: OSI Approved :: Apache Software License
Classifier: Intended Audience :: End Users/Desktop
Classifier: Intended Audience :: Developers
Classifier: Programming Language :: Python
License-File: LICENSE
